<?xml version="1.0" standalone="yes"?>
<SourceTree>
	<Source>
		<Author>
			<List>Pardo, J. D.</List>
			<List>Huttenlocker, A. K.</List>
			<List>Small, B. J.</List>
		</Author>
		<Year>2014</Year>
		<Title>An exceptionally preserved transitional lungfish from the Lower Permian of Nebraska, USA, and the origin of modern lungfishes</Title>
		<Journal>PLOS ONE</Journal>
		<Volume>9</Volume>
		<Pages>e108542</Pages>
		<Booktitle/>
		<Publisher/>
		<City/>
		<Editor/>
	</Source>
	<Taxa number="28">
		<List recon_name="Psarolepis_romeri" recon_no="377272">Psarolepis_romeri</List>
		<List recon_name="Chirodipterus_australis" recon_no="377761">Chirodipterus_australis</List>
		<List recon_name="Chirodipterus_liangcheni" recon_no="403914">Chirodipterus_liangchengi</List>
		<List recon_name="Chirodipterus_wildungensis" recon_no="372973">Chirodipterus_wildungensis</List>
		<List recon_name="Diabolepis_speratus" recon_no="372941">Diabolepis_speratus</List>
		<List recon_name="Diplocercides_kayseri" recon_no="226297">Diplocercides_kayseri</List>
		<List recon_name="Dipnorhynchus_kurikae" recon_no="391628">Dipnorhynchus_kurikae</List>
		<List recon_name="Dipnorhynchus_suessmilchi" recon_no="372947">Dipnorhynchus_sussmilchi</List>
		<List recon_name="Dipterus_valenciennesi" recon_no="259292">Dipterus_valenciennesi</List>
		<List recon_name="Eusthenopteron_foordi" recon_no="229325">Eusthenopteron_foordi</List>
		<List recon_name="Glyptolepis" recon_no="34920">Glyptolepis_spp</List>
		<List recon_name="Gogodipterus_paddyensis" recon_no="377281">Gogodipterus_paddyensis</List>
		<List recon_name="Gogonasus_andrewsae" recon_no="242714">Gogonasus_andrewsae</List>
		<List recon_name="Griphognathus_minutidens" recon_no="377509">Griphognathus_minutidens</List>
		<List recon_name="Griphognathus_whitei" recon_no="377507">Griphognathus_whitei</List>
		<List recon_name="Holodipterus_gogoensis" recon_no="377505">Holodipterus_gogoensis</List>
		<List recon_name="Melanognathus_canadensis" recon_no="250697">Melanognathus_canadensis</List>
		<List recon_name="Orlovichthys_limnatis" recon_no="391612">Orlovichthys_limnatis</List>
		<List recon_name="Pillararhynchus_longi" recon_no="377357">Pillararhynchus_longi</List>
		<List recon_name="Porolepis" recon_no="34947">Porolepis_spp</List>
		<List recon_name="Powichthys_thorsteinssoni" recon_no="401819">Powichthys_thorsteinssoni</List>
		<List recon_name="Soederberghia_groenlandica" recon_no="372956">Soederberghia_groenlandica</List>
		<List recon_name="Sorbitorhynchus_deleaskitus" recon_no="377296">Sorbitorhynchus_deleaskitus</List>
		<List recon_name="Stomiahykus_thlaodus" recon_no="377496">Stomiahykus_thlaodus</List>
		<List recon_name="Uranolophus_wyomingensis" recon_no="372944">Uranolophus_wyomingensis</List>
		<List recon_name="Youngolepis_praecursor" recon_no="403358">Youngolepis_praecursor</List>
		<List recon_name="Persephonichthys_chthonica" recon_no="306766">Persephonichthys_chthonica</List>
		<List recon_name="Rhinodipterus_kimberleyensis" recon_no="391611">Rhinodipterus_kimberleyensis</List>
	</Taxa>
	<Characters>
		<Molecular/>
		<Morphological number="70">
			<Type>Osteology</Type>
		</Morphological>
		<Behavioural/>
		<Other/>
	</Characters>
	<Analysis>
		<Type>Maximum Parsimony</Type>
	</Analysis>
	<Notes>Based on reanalysis of the original matrix.</Notes>
	<Filename>Pardo_etal_2014ab</Filename>
	<Parent>Qiao_et_Zhu_2009a</Parent>
	<Sibling/>
</SourceTree>
